{"blogPosts":[{"w":"0","facebookFix":"","author":"","pubDate":"6\/12\/23, 4:00 AM","tags":[],"cssClasses":["v73","ps307","s337","c276","ps308","s338","c277","p32","f99","ps309","s339","c278","i21","i20","ps310","s340","c279","f100","f101"],"resizeImages":"dpi=window.devicePixelRatio;if($(window).width()>=960){var a='data-src';var e=document.querySelector('.un41');if(e.hasAttribute('src')){a='src';}e.setAttribute(a,'images\/bear-hug_2-730x410-730.jpg');}else if($(window).width()>=768){var a='data-src';var e=document.querySelector('.un41');if(e.hasAttribute('src')){a='src';}e.setAttribute(a,'images\/bear-hug_2-730x410-584.jpg');}else if($(window).width()>=480){var a='data-src';var e=document.querySelector('.un41');if(e.hasAttribute('src')){a='src';}e.setAttribute(a,(dpi>1)?'images\/bear-hug_2-730x410-856.jpg':'images\/bear-hug_2-730x410-428.jpg');}else{var a='data-src';var e=document.querySelector('.un41');if(e.hasAttribute('src')){a='src';}e.setAttribute(a,(dpi>1)?'images\/bear-hug_2-730x410-570.jpg':'images\/bear-hug_2-730x410-285.jpg');}","title":"Blog Post 1","documentReady":"","documentLoad":"ldsrcset('.un50 source');","animations":"","html":"<div class=\"v73 ps307 s337 c276\">\n<div class=\"v73 ps308 s338 c277\">\n<h2 class=\"p32\"><span class=\"f99\"><a href=\"blog-post-1.html\">Make People Feel Good With These Super Easy Gestures<\/a><\/span><\/h2>\n<\/div>\n<div class=\"v73 ps309 s339 c278\">\n<picture class=\"i21 un50\">\n<source data-srcset=\"images\/bear-hug_2-730x410-285.webp 1x, images\/bear-hug_2-730x410-570.webp 2x\" srcset=\"data:image\/gif;base64,R0lGODlhAQABAIAAAAAAAP\/\/\/yH5BAEAAAAALAAAAAABAAEAAAIBRAA7\" type=\"image\/webp\" media=\"(max-width:479px)\">\n<source data-srcset=\"images\/bear-hug_2-730x410-285.jpg 1x, images\/bear-hug_2-730x410-570.jpg 2x\" srcset=\"data:image\/gif;base64,R0lGODlhAQABAIAAAAAAAP\/\/\/yH5BAEAAAAALAAAAAABAAEAAAIBRAA7\" media=\"(max-width:479px)\">\n<source data-srcset=\"images\/bear-hug_2-730x410-428.webp 1x, images\/bear-hug_2-730x410-856.webp 2x\" srcset=\"data:image\/gif;base64,R0lGODlhAQABAIAAAAAAAP\/\/\/yH5BAEAAAAALAAAAAABAAEAAAIBRAA7\" type=\"image\/webp\" media=\"(max-width:767px)\">\n<source data-srcset=\"images\/bear-hug_2-730x410-428.jpg 1x, images\/bear-hug_2-730x410-856.jpg 2x\" srcset=\"data:image\/gif;base64,R0lGODlhAQABAIAAAAAAAP\/\/\/yH5BAEAAAAALAAAAAABAAEAAAIBRAA7\" media=\"(max-width:767px)\">\n<source data-srcset=\"images\/bear-hug_2-730x410-584.webp 1x\" srcset=\"data:image\/gif;base64,R0lGODlhAQABAIAAAAAAAP\/\/\/yH5BAEAAAAALAAAAAABAAEAAAIBRAA7\" type=\"image\/webp\" media=\"(max-width:959px)\">\n<source data-srcset=\"images\/bear-hug_2-730x410-584.jpg 1x\" srcset=\"data:image\/gif;base64,R0lGODlhAQABAIAAAAAAAP\/\/\/yH5BAEAAAAALAAAAAABAAEAAAIBRAA7\" media=\"(max-width:959px)\">\n<source data-srcset=\"images\/bear-hug_2-730x410-730.webp 1x\" srcset=\"data:image\/gif;base64,R0lGODlhAQABAIAAAAAAAP\/\/\/yH5BAEAAAAALAAAAAABAAEAAAIBRAA7\" type=\"image\/webp\" media=\"(min-width:960px)\">\n<source data-srcset=\"images\/bear-hug_2-730x410-730.jpg 1x\" srcset=\"data:image\/gif;base64,R0lGODlhAQABAIAAAAAAAP\/\/\/yH5BAEAAAAALAAAAAABAAEAAAIBRAA7\" media=\"(min-width:960px)\">\n<img src=\"images\/bear-hug_2-730x410-730.jpg\" class=\"un41 i20\">\n<\/picture>\n<\/div>\n<div class=\"v73 ps310 s340 c279\">\n<p class=\"p32 f100\">The next time anyone says something you like, whether friend, neighbor, family member, whatever&hellip;. you&rsquo;ll make that person feel good if you do any one of the following:<\/p>\n<p class=\"p32 f100\"><br><\/p>\n<p class=\"p32 f100\">&nbsp;&nbsp;&nbsp;&nbsp;&bull;&nbsp;&nbsp;&nbsp;&nbsp;<span class=\"f100\">Give a thumbs-up.<\/span><\/p>\n<p class=\"p32 f100\">&nbsp;&nbsp;&nbsp;&nbsp;&bull;&nbsp;&nbsp;&nbsp;&nbsp;<span class=\"f100\">Clap your hands once.<\/span><\/p>\n<p class=\"p32 f100\">&nbsp;&nbsp;&nbsp;&nbsp;&bull;&nbsp;&nbsp;&nbsp;&nbsp;<span class=\"f100\">Drop your jaw.<\/span><\/p>\n<p class=\"p32 f100\">&nbsp;&nbsp;&nbsp;&nbsp;&bull;&nbsp;&nbsp;&nbsp;&nbsp;<span class=\"f100\">Tap your heart.<\/span><\/p>\n<p class=\"p32 f100\">&nbsp;&nbsp;&nbsp;&nbsp;&bull;&nbsp;&nbsp;&nbsp;&nbsp;<span class=\"f100\">High five, or fist bump.<\/span><\/p>\n<p class=\"p32 f100\">&nbsp;&nbsp;&nbsp;&nbsp;&bull;&nbsp;&nbsp;&nbsp;&nbsp;<span class=\"f100\">Point at them! And you can build in more emphasis:<\/span><\/p>\n<p class=\"p32\"><span class=\"f100\">&nbsp;&nbsp;&nbsp;&nbsp;<\/span><span class=\"f101\">&#x25e6;<\/span><span class=\"f100\">&nbsp;&nbsp;&nbsp;&nbsp;<\/span><span class=\"f100\">Point and wink.<\/span><\/p>\n<p class=\"p32\"><span class=\"f100\">&nbsp;&nbsp;&nbsp;&nbsp;<\/span><span class=\"f101\">&#x25e6;<\/span><span class=\"f100\">&nbsp;&nbsp;&nbsp;&nbsp;<\/span><span class=\"f100\">Point, wink, and click your tongue.<\/span><\/p>\n<p class=\"p32\"><span class=\"f100\">&nbsp;&nbsp;&nbsp;&nbsp;<\/span><span class=\"f101\">&#x25e6;<\/span><span class=\"f100\">&nbsp;&nbsp;&nbsp;&nbsp;<\/span><span class=\"f100\">Point, wink, click your tongue, and shake your hips once!<\/span><\/p>\n<p class=\"p32 f100\">Can you see how you can build upon a simple move? Don&rsquo;t be afraid to try this in the mirror. Of course you can make changes to adjust to your style! I&rsquo;m giving specifics because some people like a jumping off point. Be playful with your body language.&nbsp;&nbsp;It&rsquo;s all good, as long as you makejust a little effort. The only mistake you can make is to be &ldquo;above it all&rdquo;, and not try something a little fun.<\/p>\n<p class=\"p32 f100\"><br><\/p>\n<p class=\"p32 f100\">&ldquo;We don&rsquo;t stop playing when we get old. We get old when we stop playing.&rdquo; &mdash; George Bernard Shaw<\/p>\n<p class=\"p32 f100\"><br><\/p>\n<p class=\"p32 f100\">When you first see someone you know, and want to make them feel good:<\/p>\n<p class=\"p32 f100\">&nbsp;&nbsp;&nbsp;&nbsp;&bull;&nbsp;&nbsp;&nbsp;&nbsp;<span class=\"f100\">Say his\/her name with great enthusiasm in your voice.<\/span><\/p>\n<p class=\"p32 f100\">&nbsp;&nbsp;&nbsp;&nbsp;&bull;&nbsp;&nbsp;&nbsp;&nbsp;<span class=\"f100\">You can add extra energy by drawing his\/her name out:Jeffffrrrrrreeeeeeeee!! Hannnnaaaahhhhh!!<\/span><\/p>\n<p class=\"p32 f100\">&nbsp;&nbsp;&nbsp;&nbsp;&bull;&nbsp;&nbsp;&nbsp;&nbsp;<span class=\"f100\">Bend your knees, lean back, and clap your hands!<\/span><\/p>\n<p class=\"p32 f100\">&nbsp;&nbsp;&nbsp;&nbsp;&bull;&nbsp;&nbsp;&nbsp;&nbsp;<span class=\"f100\">Bend your knees, open your arms wide, and hold still a moment. Prepare yourself. You might get a hug this way!<\/span><\/p>\n<p class=\"p32 f100\"><br><\/p>\n<p class=\"p32 f100\">You see people do this, and maybe you do it sometimes.&nbsp;&nbsp;But few people put energy into getting better at it or doing it more often.&nbsp;&nbsp;That&rsquo;s a shame!&nbsp;&nbsp;Gestures like thisserve many good purposes. They make someone else feel good for a moment. They also warm up your expressive face and body. We&rsquo;re all expressive on the inside. The trouble is, as we grow up, some of us becomemore focused on words over actions.&nbsp;&nbsp;And in the digital world, we socialize even more with words, and less with our natural gifts in primal talk. So, when you put in just a bit of effort, you&rsquo;ll stand out. Make primal talk a habit and you&rsquo;ll light up the room!<\/p>\n<\/div>\n<\/div>"},{"w":"0","facebookFix":"","author":"","pubDate":"6\/12\/23, 4:00 AM","tags":[],"cssClasses":["v1","ps279","s306","c249","ps280","s307","c250","p1","f91","ps281","s308","c251","i19","i18","ps282","s309","c252","shm5","shm6","shm7","shm8","p31","f92"],"resizeImages":"dpi=window.devicePixelRatio;if($(window).width()>=960){var a='data-src';var e=document.querySelector('.un42');if(e.hasAttribute('src')){a='src';}e.setAttribute(a,(dpi>1)?'images\/girl-arms-over-head-730x410-548.jpg':'images\/girl-arms-over-head-730x410-274.jpg');}else if($(window).width()>=768){var a='data-src';var e=document.querySelector('.un42');if(e.hasAttribute('src')){a='src';}e.setAttribute(a,(dpi>1)?'images\/girl-arms-over-head-730x410-438.jpg':'images\/girl-arms-over-head-730x410-219.jpg');}else if($(window).width()>=480){var a='data-src';var e=document.querySelector('.un42');if(e.hasAttribute('src')){a='src';}e.setAttribute(a,(dpi>1)?'images\/girl-arms-over-head-730x410-856.jpg':'images\/girl-arms-over-head-730x410-428.jpg');}else{var a='data-src';var e=document.querySelector('.un42');if(e.hasAttribute('src')){a='src';}e.setAttribute(a,(dpi>1)?'images\/girl-arms-over-head-730x410-570.jpg':'images\/girl-arms-over-head-730x410-285.jpg');}","title":"Blog Post","documentReady":"","documentLoad":"ldsrcset('.un49 source');","animations":"","html":"<div class=\"v1 ps279 s306 c249\">\n<div class=\"v1 ps280 s307 c250\">\n<h2 class=\"p1 f91\">F<span class=\"f91\"><a href=\"blog-post.html\">eel Ready For Anything When You Strike This Pose<\/a><\/span><\/h2>\n<\/div>\n<div class=\"v1 ps281 s308 c251\">\n<picture class=\"i19 un49\">\n<source data-srcset=\"images\/girl-arms-over-head-730x410-285.webp 1x, images\/girl-arms-over-head-730x410-570.webp 2x\" srcset=\"data:image\/gif;base64,R0lGODlhAQABAIAAAAAAAP\/\/\/yH5BAEAAAAALAAAAAABAAEAAAIBRAA7\" type=\"image\/webp\" media=\"(max-width:479px)\">\n<source data-srcset=\"images\/girl-arms-over-head-730x410-285.jpg 1x, images\/girl-arms-over-head-730x410-570.jpg 2x\" srcset=\"data:image\/gif;base64,R0lGODlhAQABAIAAAAAAAP\/\/\/yH5BAEAAAAALAAAAAABAAEAAAIBRAA7\" media=\"(max-width:479px)\">\n<source data-srcset=\"images\/girl-arms-over-head-730x410-428.webp 1x, images\/girl-arms-over-head-730x410-856.webp 2x\" srcset=\"data:image\/gif;base64,R0lGODlhAQABAIAAAAAAAP\/\/\/yH5BAEAAAAALAAAAAABAAEAAAIBRAA7\" type=\"image\/webp\" media=\"(max-width:767px)\">\n<source data-srcset=\"images\/girl-arms-over-head-730x410-428.jpg 1x, images\/girl-arms-over-head-730x410-856.jpg 2x\" srcset=\"data:image\/gif;base64,R0lGODlhAQABAIAAAAAAAP\/\/\/yH5BAEAAAAALAAAAAABAAEAAAIBRAA7\" media=\"(max-width:767px)\">\n<source data-srcset=\"images\/girl-arms-over-head-730x410-219.webp 1x, images\/girl-arms-over-head-730x410-438.webp 2x\" srcset=\"data:image\/gif;base64,R0lGODlhAQABAIAAAAAAAP\/\/\/yH5BAEAAAAALAAAAAABAAEAAAIBRAA7\" type=\"image\/webp\" media=\"(max-width:959px)\">\n<source data-srcset=\"images\/girl-arms-over-head-730x410-219.jpg 1x, images\/girl-arms-over-head-730x410-438.jpg 2x\" srcset=\"data:image\/gif;base64,R0lGODlhAQABAIAAAAAAAP\/\/\/yH5BAEAAAAALAAAAAABAAEAAAIBRAA7\" media=\"(max-width:959px)\">\n<source data-srcset=\"images\/girl-arms-over-head-730x410-274.webp 1x, images\/girl-arms-over-head-730x410-548.webp 2x\" srcset=\"data:image\/gif;base64,R0lGODlhAQABAIAAAAAAAP\/\/\/yH5BAEAAAAALAAAAAABAAEAAAIBRAA7\" type=\"image\/webp\" media=\"(min-width:960px)\">\n<source data-srcset=\"images\/girl-arms-over-head-730x410-274.jpg 1x, images\/girl-arms-over-head-730x410-548.jpg 2x\" srcset=\"data:image\/gif;base64,R0lGODlhAQABAIAAAAAAAP\/\/\/yH5BAEAAAAALAAAAAABAAEAAAIBRAA7\" media=\"(min-width:960px)\">\n<img src=\"images\/girl-arms-over-head-730x410-548.jpg\" class=\"un42 i18\">\n<\/picture>\n<\/div>\n<div class=\"shape2 v1 ps282 s309 c252\">\n<div class=\"shm5\"><\/div>\n<div class=\"shm6\"><\/div>\n<div class=\"shm7\"><\/div>\n<div class=\"shm8\"><\/div>\n<p class=\"p31 f92\">Try throwing your arms over your head.&nbsp; Almost everyone has done this.&nbsp; This time, allow yourself to hold it a little longer than usual.&nbsp;<\/p>\n<p class=\"p31 f92\">Circus performers do this bow at the end of their routine, the culmination of years of hard work.&nbsp; This bow plays to the farthest seat in the arena.&nbsp; Primates hit this posture when they want to assert themselves.&nbsp; Victorious athletes do this. Even athletes who were born blind, and never seen throw their arms up, assume this posture when ecstatic.That&rsquo;s how innate this pose is.<\/p>\n<p class=\"p31 f92\">I&rsquo;ve encouraged many folks to do this, because I know it makes me feel capable.&nbsp; It makes you feel strong. I know for a fact that audiences around the world understand this.<\/p>\n<p class=\"p31 f92\">I&rdquo;m simply opening up here, and lifting my chest.&nbsp; &nbsp;&nbsp;<\/p>\n<p class=\"p31 f92\">As I do this , testosterone goes up. This makes me ready for a challenge, and boosts my confidence<\/p>\n<p class=\"p31 f92\">And don&rsquo;t think for a minute that testosterone is only a male hormone.&nbsp; Women have it, too.<\/p>\n<p class=\"p31 f92\">And male or female, you may be interested to know that your&nbsp; Cortisol&nbsp; levels goes down.&nbsp; &ldquo;The stress hormone&rdquo;.<\/p>\n<p class=\"p31 f92\">Try this pose in private for&nbsp; minute, before you start your work day, andnotice how you feel. Can you see how your body language talks to yourself, not just others ?!<\/p>\n<\/div>\n<\/div>"}],"blogPostsPerPage":5,"devices":["default:960","768:768","480:480","320:320"],"css":{"768":{"f101":".f101{font-family:\"Lucida Grande\", \"Lucida Sans Unicode\", \"Lucida Sans\", Geneva, Verdana, sans-serif;font-size:12px;font-size:calc(12px * var(--f))}","c277":".c277{height:75px}","f99":".f99{font-size:28px;font-size:calc(28px * var(--f));line-height:1.322}","f100":".f100{font-size:12px;font-size:calc(12px * var(--f));line-height:1.751}","ps308":".ps308{margin-left:96px}","s339":".s339{min-width:584px;width:584px;min-height:328px;height:328px}","c279":".c279{height:671px}","i20":".i20{width:584px;height:328px}","ps310":".ps310{margin-left:96px;margin-top:27px}","s340":".s340{min-width:602px;width:602px;min-height:671px}","s338":".s338{min-width:576px;width:576px;min-height:75px}","ps309":".ps309{margin-left:114px;margin-top:41px}","s337":".s337{min-width:768px;min-height:1142px}"},"default":{"s337":".s337{width:100%;min-width:960px;min-height:1427px}","ps310":".ps310{position:relative;margin-left:120px;margin-top:33px}","c278":".c278{z-index:13;pointer-events:auto}","c250":".c250{z-index:16;pointer-events:auto;overflow:hidden;height:94px}","i18":".i18{position:absolute;left:0;width:274px;height:154px;top:88px;border:0}","s306":".s306{width:100%;min-width:960px;min-height:698px}","ps279":".ps279{position:relative;margin-top:0}","p1":".p1{text-indent:0;padding-bottom:0;padding-right:0;text-align:left}","shm7":".shm7{display:block;float:left;clear:left;width:0;height:305px;shape-outside:polygon(0px 0px, 0px 305px, 0px 305px, 0px 0px);-webkit-shape-outside:polygon(0px 0px, 0px 305px, 0px 305px, 0px 0px)}","s338":".s338{min-width:720px;width:720px;min-height:94px}","i19":".i19{width:100%;height:100%;display:inline-block;-webkit-transform:translate3d(0,0,0)}","v73":".v73{display:inline-block;vertical-align:top}","p31":".p31{text-indent:0;padding-bottom:10px;padding-right:0;text-align:left}","ps282":".ps282{position:relative;margin-left:120px;margin-top:-247px}","c279":".c279{z-index:14;pointer-events:auto;overflow:hidden;height:839px}","ps308":".ps308{position:relative;margin-left:120px;margin-top:0}","s307":".s307{min-width:720px;width:720px;min-height:94px}","p32":".p32{text-indent:0;padding-bottom:0;padding-right:0;text-align:left}","f100":".f100{font-family:Lato;font-size:15px;font-size:calc(15px * var(--f));line-height:1.668;font-weight:400;font-style:normal;text-decoration:none;text-transform:none;letter-spacing:normal;color:#404040;background-color:initial;text-shadow:none}","ps280":".ps280{position:relative;margin-left:120px;margin-top:0}","c251":".c251{z-index:18;pointer-events:auto}","shm8":".shm8{display:block;float:right;clear:right;height:305px;width:0;shape-outside:polygon(0px 0px, 0px 305px, 0px 305px, 0px 0px);-webkit-shape-outside:polygon(0px 0px, 0px 305px, 0px 305px, 0px 0px)}","s339":".s339{min-width:730px;width:730px;min-height:410px;height:410px}","c252":".c252{z-index:17;pointer-events:auto;font-family:Lato;font-size:15px;font-size:calc(15px * var(--f));line-height:1.668;font-weight:400;font-style:normal;text-decoration:none;text-transform:none;letter-spacing:normal;color:initial;background-color:initial;overflow:hidden;height:560px}","s308":".s308{min-width:274px;width:274px;min-height:330px;height:330px}","c276":".c276{z-index:11}","f91":".f91{font-family:Lato;font-size:36px;font-size:calc(36px * var(--f));line-height:1.307;font-weight:300;font-style:normal;text-decoration:none;text-transform:none;letter-spacing:normal;color:#000;background-color:initial;text-shadow:none}","f101":".f101{font-family:Lato;font-size:15px;font-size:calc(15px * var(--f));line-height:1.668;font-weight:400;font-style:normal;text-decoration:none;text-transform:none;letter-spacing:normal;color:#404040;background-color:initial;text-shadow:none}","f99":".f99{font-family:Lato;font-size:36px;font-size:calc(36px * var(--f));line-height:1.307;font-weight:300;font-style:normal;text-decoration:underline;text-transform:none;letter-spacing:normal;color:#54387d;background-color:initial;text-shadow:none}","shm5":".shm5{display:block;float:left;clear:left;width:720px;height:255px;shape-outside:polygon(0px 255px, 1px 255px, 1px 166px, 277px 166px, 277px 165px, 279px 165px, 279px 164px, 280px 164px, 280px 162px, 281px 162px, 281px 1px, 280px 1px, 280px 0px, 0px 0px);-webkit-shape-outside:polygon(0px 255px, 1px 255px, 1px 166px, 277px 166px, 277px 165px, 279px 165px, 279px 164px, 280px 164px, 280px 162px, 281px 162px, 281px 1px, 280px 1px, 280px 0px, 0px 0px)}","i20":".i20{position:absolute;left:0;width:730px;height:410px;top:0;border:0}","v1":".v1{display:inline-block;vertical-align:top}","c249":".c249{z-index:15}","f92":".f92{font-family:Lato;font-size:15px;font-size:calc(15px * var(--f));line-height:1.668;font-weight:400;font-style:normal;text-decoration:none;text-transform:none;letter-spacing:normal;color:#404040;background-color:initial;text-shadow:none}","ps309":".ps309{position:relative;margin-left:143px;margin-top:51px}","i21":".i21{width:100%;height:100%;display:inline-block;-webkit-transform:translate3d(0,0,0)}","s340":".s340{min-width:753px;width:753px;min-height:839px}","s309":".s309{min-width:720px;width:720px;min-height:560px}","ps281":".ps281{position:relative;margin-left:120px;margin-top:-39px}","c277":".c277{z-index:12;pointer-events:auto;overflow:hidden;height:94px}","ps307":".ps307{position:relative;margin-top:0}","shm6":".shm6{display:block;float:right;clear:right;height:255px;width:0;shape-outside:polygon(0px 0px, 0px 255px, 0px 255px, 0px 0px);-webkit-shape-outside:polygon(0px 0px, 0px 255px, 0px 255px, 0px 0px)}"},"480":{"f101":".f101{font-family:\"Lucida Grande\", \"Lucida Sans Unicode\", \"Lucida Sans\", Geneva, Verdana, sans-serif;font-size:24px;font-size:calc(24px * var(--f));line-height:1.626}","c277":".c277{height:104px}","f99":".f99{font-size:30px;font-size:calc(30px * var(--f));line-height:1.334}","f100":".f100{font-size:24px;font-size:calc(24px * var(--f))}","ps308":".ps308{margin-left:26px}","s339":".s339{min-width:428px;width:428px;min-height:261px;height:261px}","c279":".c279{height:2619px}","i20":".i20{width:428px;height:240px;top:11px}","ps310":".ps310{margin-left:26px}","s340":".s340{min-width:438px;width:438px;min-height:2619px}","s338":".s338{min-width:428px;width:428px;min-height:104px}","ps309":".ps309{margin-left:26px;margin-top:31px}","s337":".s337{min-width:480px;min-height:3048px}"},"320":{"f101":".f101{font-family:\"Lucida Grande\", \"Lucida Sans Unicode\", \"Lucida Sans\", Geneva, Verdana, sans-serif;font-size:16px;font-size:calc(16px * var(--f));line-height:1.688}","c277":".c277{height:69px}","f99":".f99{font-size:20px;font-size:calc(20px * var(--f));line-height:1.351}","f100":".f100{font-size:16px;font-size:calc(16px * var(--f));line-height:1.688}","ps308":".ps308{margin-left:17px}","s339":".s339{min-width:285px;width:285px;min-height:174px;height:174px}","c279":".c279{height:1746px}","i20":".i20{width:285px;height:160px;top:7px}","ps310":".ps310{margin-left:17px;margin-top:22px}","s340":".s340{min-width:292px;width:292px;min-height:1746px}","s338":".s338{min-width:285px;width:285px;min-height:69px}","ps309":".ps309{margin-left:17px;margin-top:21px}","s337":".s337{min-width:320px;min-height:2032px}"}},"mq":{"768":"(min-width:768px) and (max-width:959px)","480":"(min-width:480px) and (max-width:767px)","320":"(max-width:479px)"},"blogPostsMargin":{"768":64,"default":80,"480":41,"320":27}}